mysql_tools_service/server.py
mysql_tools_service-0.1.7.dist-info/METADATA
mysql_tools_service-0.1.7.dist-info/WHEEL
mysql_tools_service-0.1.7.dist-info/entry_points.txt
mysql_tools_service-0.1.7.dist-info/top_level.txt
mysql_tools_service-0.1.7.dist-info/RECORD
