Metadata-Version: 2.4
Name: mysql-tools-service
Version: 0.1.7
Summary: mysql的增删改查、xlsx文件的url转为json
Requires-Python: >=3.12
Requires-Dist: mcp[cli]>=1.12.4
Requires-Dist: openpyxl>=3.1.5
Requires-Dist: pandas>=2.3.1
Requires-Dist: pymysql>=1.1.1
Requires-Dist: requests>=2.32.4
